setup.py
normal_bin_distributions/Binomialdistribution.py
normal_bin_distributions/Gaussiandistribution.py
normal_bin_distributions/Generaldistribution.py
normal_bin_distributions/__init__.py
normal_bin_distributions.egg-info/PKG-INFO
normal_bin_distributions.egg-info/SOURCES.txt
normal_bin_distributions.egg-info/dependency_links.txt
normal_bin_distributions.egg-info/not-zip-safe
normal_bin_distributions.egg-info/top_level.txt