Metadata-Version: 1.0
Name: normal-bin-distributions
Version: 1.3
Summary: Binomial and Gaussian distributions
Home-page: UNKNOWN
Author: Victor Emenike
Author-email: test@someemail.com
License: UNKNOWN
Platform: UNKNOWN
